mdtemplate/__init__.py
mdtemplate/__main__.py
mdtemplate/py.typed
mdtemplate/table/__init__.py
mdtemplate/table/presets/__init__.py
mdtemplate/table/presets/scoop.py
mdtemplate/table/presets/userscripts.py
mdtemplate/utils/__init__.py
mdtemplate/utils/repo.py
md_template-0.2.1.dist-info/METADATA
md_template-0.2.1.dist-info/WHEEL
md_template-0.2.1.dist-info/entry_points.txt
md_template-0.2.1.dist-info/licenses/LICENSE
md_template-0.2.1.dist-info/RECORD
