Metadata-Version: 2.3
Name: md-template
Version: 0.2.1
Summary: A tool to generate markdown tables based on a set of files
Project-URL: Homepage, https://github.com/jcwillox/md-template
Project-URL: Repository, https://github.com/jcwillox/md-template
Project-URL: Release Notes, https://github.com/jcwillox/md-template/releases
Project-URL: Issues, https://github.com/jcwillox/md-template/issues
Project-URL: Funding, https://ko-fi.com/jcwillox
Author-email: Josh Willox <joshwillox@gmail.com>
Classifier: License :: OSI Approved :: MIT License
Classifier: Operating System :: OS Independent
Classifier: Programming Language :: Python :: 3.8
Classifier: Programming Language :: Python :: 3.9
Classifier: Programming Language :: Python :: 3.10
Classifier: Programming Language :: Python :: 3.11
Classifier: Programming Language :: Python :: 3.12
Classifier: Typing :: Typed
Requires-Python: >=3.8
Provides-Extra: full
Requires-Dist: natsort>=8.4.0; extra == 'full'
Requires-Dist: pyyaml>=6.0.2; extra == 'full'
Provides-Extra: natsort
Requires-Dist: natsort>=8.4.0; extra == 'natsort'
